odoo/addons/edi_sale_ubl_oca/README.rst
odoo/addons/edi_sale_ubl_oca/__init__.py
odoo/addons/edi_sale_ubl_oca/__manifest__.py
odoo/addons/edi_sale_ubl_oca/components/__init__.py
odoo/addons/edi_sale_ubl_oca/components/listeners.py
odoo/addons/edi_sale_ubl_oca/data/edi_state.xml
odoo/addons/edi_sale_ubl_oca/demo/edi_exchange_type.xml
odoo/addons/edi_sale_ubl_oca/i18n/edi_sale_ubl_oca.pot
odoo/addons/edi_sale_ubl_oca/i18n/it.po
odoo/addons/edi_sale_ubl_oca/models/__init__.py
odoo/addons/edi_sale_ubl_oca/models/sale_order.py
odoo/addons/edi_sale_ubl_oca/readme/CONTRIBUTORS.md
odoo/addons/edi_sale_ubl_oca/readme/DESCRIPTION.md
odoo/addons/edi_sale_ubl_oca/static/description/icon.png
odoo/addons/edi_sale_ubl_oca/static/description/index.html
odoo/addons/edi_sale_ubl_oca/tests/__init__.py
odoo/addons/edi_sale_ubl_oca/tests/common.py
odoo/addons/edi_sale_ubl_oca/tests/test_order_state.py
odoo/addons/edi_sale_ubl_oca/views/sale_order.xml
odoo_addon_edi_sale_ubl_oca-18.0.1.0.2.dist-info/METADATA
odoo_addon_edi_sale_ubl_oca-18.0.1.0.2.dist-info/WHEEL
odoo_addon_edi_sale_ubl_oca-18.0.1.0.2.dist-info/top_level.txt
odoo_addon_edi_sale_ubl_oca-18.0.1.0.2.dist-info/RECORD
