Metadata-Version: 2.1
Name: odoo-addon-edi_sale_ubl_oca
Version: 18.0.1.0.2
Requires-Python: >=3.10
Requires-Dist: odoo-addon-edi_sale_oca==18.0.*
Requires-Dist: odoo-addon-edi_state_oca==18.0.*
Requires-Dist: odoo-addon-edi_ubl_oca==18.0.*
Requires-Dist: odoo==18.0.*
Summary: Configuration and special behaviors for EDI UBL exchanges related to sales.
Home-page: https://github.com/OCA/edi-framework
License: AGPL-3
Author: Camptocamp,Odoo Community Association (OCA)
Author-email: support@odoo-community.org
Classifier: Programming Language :: Python
Classifier: Framework :: Odoo
Classifier: Framework :: Odoo :: 18.0
Classifier: License :: OSI Approved :: GNU Affero General Public License v3
Classifier: Development Status :: 3 - Alpha
